drb/drivers/csv/__init__.py
drb/drivers/csv/_version.py
drb/drivers/csv/factory.py
drb/drivers/csv/nodes.py
drb/topics/csv/__init__.py
drb/topics/csv/cortex.yml
drb_driver_csv-1.1.0.dist-info/LICENSE.txt
drb_driver_csv-1.1.0.dist-info/METADATA
drb_driver_csv-1.1.0.dist-info/WHEEL
drb_driver_csv-1.1.0.dist-info/entry_points.txt
drb_driver_csv-1.1.0.dist-info/top_level.txt
drb_driver_csv-1.1.0.dist-info/RECORD
