Metadata-Version: 2.1
Name: drb-driver-csv
Version: 1.1.0
Summary: DRB Python CSV Driver
Home-page: https://gitlab.com/drb-python/impl/csv
Author: GAEL Systems
Author-email: drb-python@gael.fr
License: LGPLv3
Project-URL: Source, https://gitlab.com/drb-python/impl/csv
Classifier: Programming Language :: Python :: 3.8
Classifier: Environment :: Plugins
Classifier: License :: OSI Approved :: GNU Lesser General Public License v3 (LGPLv3)
Requires-Python: >=3.8
License-File: LICENSE.txt
Requires-Dist: drb ~=2.2.0
Requires-Dist: pandas >=2.0.1
